<?xml version="1.0" encoding="UTF-8"?>

<song id="1371">
 <title>Blush Funk</title>
 <status v="A">Active</status>
 <bitrate>128</bitrate>
 <samplerate>44100</samplerate>
 <rating votes="19">4.0</rating>
 
 <songlength>146</songlength>
 <locked>False</locked>
 <locked_until>2018-05-04 20:49:07</locked_until>
 <lastplayed>2018-04-03 18:31:54</lastplayed>
 <platform id="6">MOD</platform>
 <type id="11">Musicdisk</type>
 <pouetid>56248</pouetid>
 
 
 
 <artists>
  <artist id="257">Cutcreator</artist>
 </artists>
 <groups>
  <group id="143">Static Bytes</group>
 </groups>
 
 <tags>
 </tags>
 <links>
 
 </links>
</song>