<?xml version="1.0" encoding="UTF-8"?>

<song id="40911">
 <title>Artificial</title>
 <status v="A">Active</status>
 <bitrate>0</bitrate>
 <samplerate>0</samplerate>
 <rating votes="9">3.5556</rating>
 
 <songlength>215</songlength>
 <locked>False</locked>
 <locked_until>2017-11-22 04:30:57</locked_until>
 <lastplayed>2017-11-02 21:57:07</lastplayed>
 <platform id="6">MOD</platform>
 
 
 
 
 
 <artists>
  <artist id="806">Moby</artist>
 </artists>
 <groups>
  
 </groups>
 
 <tags>
 </tags>
 <links>
 
 </links>
</song>