<?xml version="1.0" encoding="UTF-8"?>

<song id="8506">
 <title>Waterworld (Dolphin Kingdom)</title>
 <status v="A">Active</status>
 <bitrate>192</bitrate>
 <samplerate>44100</samplerate>
 <rating votes="97">4.2371</rating>
 
 <songlength>327</songlength>
 <locked>True</locked>
 <locked_until>2018-06-24 11:59:23</locked_until>
 <lastplayed>2018-05-23 21:47:48</lastplayed>
 <platform id="8">IT</platform>
 
 
 
 
 
 <artists>
  <artist id="260">Cyborg Jeff</artist>
 </artists>
 <groups>
  
 </groups>
 
 <tags>
  <tag>animal</tag>
  
  <tag>water</tag>
  
 </tags>
 <links>
 
 </links>
</song>