<?xml version="1.0" encoding="UTF-8"?>

<song id="44581">
 <title>zwerge6</title>
 <status v="A">Active</status>
 <bitrate>0</bitrate>
 <samplerate>44100</samplerate>
 <rating votes="6">3.6667</rating>
 <info>Download:  http://amp.dascene.net/downmod.php?index=76153</info>
 <songlength>128</songlength>
 <locked>True</locked>
 <locked_until>2018-07-15 21:11:41</locked_until>
 <lastplayed>2018-06-10 11:36:59</lastplayed>
 <platform id="6">MOD</platform>
 
 
 
 
 
 <artists>
  <artist id="1591">WOTW</artist>
 </artists>
 <groups>
  <group id="885">Sun Project</group>
 </groups>
 
 <tags>
 </tags>
 <links>
 
 </links>
</song>