<?xml version="1.0" encoding="UTF-8"?>

<song id="44641">
 <title>Mind Meltation</title>
 <status v="A">Active</status>
 <bitrate>0</bitrate>
 <samplerate>44100</samplerate>
 <rating votes="8">1.75</rating>
 
 <songlength>220</songlength>
 <locked>True</locked>
 <locked_until>2018-07-19 11:41:13</locked_until>
 <lastplayed>2018-05-29 06:29:25</lastplayed>
 <platform id="6">MOD</platform>
 <type id="2">Demo</type>
 <pouetid>18585</pouetid>
 
 
 
 <artists>
  <artist id="5775">Zadd</artist>
 </artists>
 <groups>
  
 </groups>
 
 <tags>
  <tag>letthebasskick</tag>
  
  <tag>Rave</tag>
  
 </tags>
 <links>
 
 </links>
</song>