<?xml version="1.0" encoding="UTF-8"?>

<song id="4094">
 <title>Mirror Images</title>
 <status v="A">Active</status>
 <bitrate>127</bitrate>
 <samplerate>44100</samplerate>
 <rating votes="30">4.1</rating>
 
 <songlength>211</songlength>
 <locked>False</locked>
 <locked_until>None</locked_until>
 <lastplayed>2017-05-06 18:04:42</lastplayed>
 <platform id="3">XM</platform>
 <type id="3">Oldskool</type>
 
 
 
 
 <artists>
  <artist id="669">Lizardking</artist>
 </artists>
 <groups>
  <group id="29">The Black Lotus</group><group id="156">Triton</group>
 </groups>
 
 <tags>
  <tag>1995</tag>
  
 </tags>
 <links>
 
 </links>
</song>