<?xml version="1.0" encoding="UTF-8"?>

<song id="31704">
 <title>Delayed in time.</title>
 <status v="A">Active</status>
 <bitrate>0</bitrate>
 <samplerate>0</samplerate>
 <rating votes="12">3.3333</rating>
 
 <songlength>112</songlength>
 <locked>False</locked>
 <locked_until>2017-10-04 20:48:11</locked_until>
 <lastplayed>2017-09-27 14:29:46</lastplayed>
 <platform id="7">S3M</platform>
 
 
 
 
 
 <artists>
  <artist id="1211">The Zapper</artist>
 </artists>
 <groups>
  
 </groups>
 
 <tags>
 </tags>
 <links>
 
 </links>
</song>