<?xml version="1.0" encoding="UTF-8"?>

<song id="16098">
 <title>You really wanna party with me</title>
 <status v="A">Active</status>
 <bitrate>127</bitrate>
 <samplerate>44100</samplerate>
 <rating votes="12">1.8333</rating>
 
 <songlength>200</songlength>
 <locked>False</locked>
 <locked_until>2018-05-28 08:25:21</locked_until>
 <lastplayed>2018-04-05 10:44:54</lastplayed>
 
 
 
 
 
 
 <artists>
  <artist id="233">CONS</artist>
 </artists>
 <groups>
  
 </groups>
 
 <tags>
  <tag>CommercialSamples</tag>
  
  <tag>Rap</tag>
  
 </tags>
 <links>
 
 </links>
</song>