<?xml version="1.0" encoding="UTF-8"?>

<song id="37318">
 <title>Roll&#39; em</title>
 <status v="A">Active</status>
 <bitrate>279</bitrate>
 <samplerate>44100</samplerate>
 <rating votes="12">3.3333</rating>
 
 <songlength>161</songlength>
 <locked>False</locked>
 <locked_until>2018-06-03 04:45:13</locked_until>
 <lastplayed>2018-05-14 00:39:53</lastplayed>
 <platform id="5">AY/YM</platform>
 
 
 
 
 
 <artists>
  <artist id="4242">Andy Fer</artist>
 </artists>
 <groups>
  
 </groups>
 
 <tags>
 </tags>
 <links>
 
 </links>
</song>