<?xml version="1.0" encoding="UTF-8"?>

<song id="12912">
 <title>Candy Coast</title>
 <status v="A">Active</status>
 <bitrate>192</bitrate>
 <samplerate>44100</samplerate>
 <rating votes="40">4.275</rating>
 <info>Wiklund and Nyhlin bring you a 170kb tune made with happines. :D this tune is made in Milkytracker :)</info>
 <songlength>139</songlength>
 <locked>True</locked>
 <locked_until>2018-07-07 01:09:25</locked_until>
 <lastplayed>2018-06-07 00:49:32</lastplayed>
 <platform id="3">XM</platform>
 <type id="1">Chiptune</type>
 
 
 
 
 <artists>
  <artist id="2087">Wiklund</artist>
 </artists>
 <groups>
  
 </groups>
 
 <tags>
  <tag>Chiptune</tag>
  
  <tag>food</tag>
  
 </tags>
 <links>
 
 </links>
</song>