<?xml version="1.0" encoding="UTF-8"?>

<song id="23187">
 <title>Waiting for the Solo</title>
 <status v="A">Active</status>
 <bitrate>128</bitrate>
 <samplerate>44100</samplerate>
 <rating votes="16">3.1875</rating>
 
 <songlength>347</songlength>
 <locked>False</locked>
 <locked_until>2018-03-04 18:00:27</locked_until>
 <lastplayed>2018-02-11 19:10:26</lastplayed>
 <platform id="20">PC-custom</platform>
 
 
 
 
 
 <artists>
  <artist id="980">Rage</artist>
 </artists>
 <groups>
  
 </groups>
 
 <tags>
  <tag>Guitar</tag>
  
  <tag>GuitarSolo</tag>
  
  <tag>synthpop</tag>
  
 </tags>
 <links>
 
  <link>
    <url>http://www.youtube.com/watch?v=DqMxvn8TEj0</url>
    <comment></comment>
    <type id="2">
        <name>YouTube</name>
        <icon>/static/media/linkicons/youtube-icon_.png</icon>
    </type>
  </link>
 
 </links>
</song>