<?xml version="1.0" encoding="UTF-8"?>

<song id="26672">
 <title>Epica 5</title>
 <status v="A">Active</status>
 <bitrate>128</bitrate>
 <samplerate>44100</samplerate>
 <rating votes="20">3.6</rating>
 
 <songlength>327</songlength>
 <locked>False</locked>
 <locked_until>2018-04-22 05:31:31</locked_until>
 <lastplayed>2018-03-18 18:46:59</lastplayed>
 <platform id="3">XM</platform>
 <type id="8">Newschool</type>
 
 
 
 
 <artists>
  <artist id="2005">Jakim</artist>
 </artists>
 <groups>
  
 </groups>
 
 <tags>
 </tags>
 <links>
 
 </links>
</song>