<?xml version="1.0" encoding="UTF-8"?>

<song id="11285">
 <title>Tetris 2 - Title [AY]</title>
 <status v="A">Active</status>
 <bitrate>320</bitrate>
 <samplerate>44100</samplerate>
 <rating votes="49">3.7347</rating>
 
 <songlength>180</songlength>
 <locked>True</locked>
 <locked_until>2018-07-01 11:29:15</locked_until>
 <lastplayed>2018-05-27 02:15:34</lastplayed>
 <platform id="5">AY/YM</platform>
 <type id="7">Game</type>
 <pouetid>26731</pouetid>
 
 
 
 <artists>
  <artist id="1724">Fuxoft</artist>
 </artists>
 <groups>
  
 </groups>
 
 <tags>
  <tag>game</tag>
  
 </tags>
 <links>
 
 </links>
</song>