<?xml version="1.0" encoding="UTF-8"?>

<song id="234">
 <title>Tower Assault</title>
 <status v="A">Active</status>
 <bitrate>128</bitrate>
 <samplerate>44100</samplerate>
 <rating votes="8">3.25</rating>
 
 <songlength>76</songlength>
 <locked>False</locked>
 <locked_until>2017-06-28 06:48:25</locked_until>
 <lastplayed>2017-06-01 07:49:25</lastplayed>
 
 
 
 
 
 
 <artists>
  <artist id="38">Allister Brimble</artist>
 </artists>
 <groups>
  
 </groups>
 
 <tags>
 </tags>
 <links>
 
 </links>
</song>