<?xml version="1.0" encoding="UTF-8"?>

<song id="14550">
 <title>Torha</title>
 <status v="A">Active</status>
 <bitrate>127</bitrate>
 <samplerate>44100</samplerate>
 <rating votes="15">2.7333</rating>
 
 <songlength>523</songlength>
 <locked>False</locked>
 <locked_until>None</locked_until>
 <lastplayed>2017-05-21 19:15:43</lastplayed>
 <platform id="6">MOD</platform>
 
 
 
 
 
 <artists>
  <artist id="2269">Badsnail</artist>
 </artists>
 <groups>
  
 </groups>
 
 <tags>
  <tag>long</tag>
  
 </tags>
 <links>
 
 </links>
</song>