<?xml version="1.0" encoding="UTF-8"?>

<song id="11060">
 <title>Dark Angel 2-2</title>
 <status v="A">Active</status>
 <bitrate>320</bitrate>
 <samplerate>44100</samplerate>
 <rating votes="11">2.8182</rating>
 <info>Created using Soundmon v2.0 or v2.2</info>
 <songlength>140</songlength>
 <locked>False</locked>
 <locked_until>2018-04-27 00:48:03</locked_until>
 <lastplayed>2018-04-04 20:21:43</lastplayed>
 <platform id="13">AMIGA-custom</platform>
 <type id="1">Chiptune</type>
 
 
 
 
 <artists>
  <artist id="1612">Zzzax</artist>
 </artists>
 <groups>
  
 </groups>
 
 <tags>
 </tags>
 <links>
 
 </links>
</song>