<?xml version="1.0" encoding="UTF-8"?>

<song id="11078">
 <title>Paradise Lost</title>
 <status v="A">Active</status>
 <bitrate>192</bitrate>
 <samplerate>44100</samplerate>
 <rating votes="17">3.2941</rating>
 <info>((basehead/fm+imphobia))
- hope ya like the weird tune... i think it&#39;s pretty original
samples: darkstar, juno, krystal, sh, x-static goldmine (cd)
</info>
 <songlength>416</songlength>
 <locked>False</locked>
 <locked_until>2017-07-20 10:53:14</locked_until>
 <lastplayed>2017-07-12 17:42:31</lastplayed>
 <platform id="7">S3M</platform>
 <type id="3">Oldskool</type>
 
 
 
 
 <artists>
  <artist id="95">Basehead</artist>
 </artists>
 <groups>
  
 </groups>
 
 <tags>
 </tags>
 <links>
 
 </links>
</song>