<?xml version="1.0" encoding="UTF-8"?>

<song id="11081">
 <title>Human (We are Killers-REmix)</title>
 <status v="C">Removed By Request</status>
 <bitrate>192</bitrate>
 <samplerate>44100</samplerate>
 <rating votes="2">4.0</rating>
 
 <songlength>222</songlength>
 <locked>True</locked>
 <locked_until>None</locked_until>
 <lastplayed>Never</lastplayed>
 <platform id="8">IT</platform>
 <type id="5">Remix</type>
 
 
 
 
 <artists>
  <artist id="15">Acidline</artist>
 </artists>
 <groups>
  
 </groups>
 
 <tags>
 </tags>
 <links>
 
 </links>
</song>