<?xml version="1.0" encoding="UTF-8"?>

<song id="869">
 <title>Autumn in Budapest</title>
 <status v="A">Active</status>
 <bitrate>0</bitrate>
 <samplerate>0</samplerate>
 <rating votes="50">3.9</rating>
 
 <songlength>240</songlength>
 <locked>False</locked>
 <locked_until>2017-12-21 05:43:42</locked_until>
 <lastplayed>2017-12-03 10:53:11</lastplayed>
 <platform id="3">XM</platform>
 <type id="11">Musicdisk</type>
 <pouetid>137</pouetid>
 
 
 
 <artists>
  <artist id="166">Carlos</artist>
 </artists>
 <groups>
  
 </groups>
 
 <tags>
  <tag>ElevatorMusic</tag>
  
  <tag>Geography</tag>
  
  <tag>Jazz</tag>
  
  <tag>Piano</tag>
  
 </tags>
 <links>
 
 </links>
</song>