<?xml version="1.0" encoding="UTF-8"?>

<song id="30130">
 <title>Loving Thoughts</title>
 <status v="A">Active</status>
 <bitrate>320</bitrate>
 <samplerate>48000</samplerate>
 <rating votes="16">3.9375</rating>
 
 <songlength>286</songlength>
 <locked>False</locked>
 <locked_until>2018-06-07 23:22:57</locked_until>
 <lastplayed>2018-05-21 04:46:55</lastplayed>
 <platform id="6">MOD</platform>
 <type id="12">Diskmag</type>
 <pouetid>20023</pouetid>
 
 
 
 <artists>
  <artist id="1915">Curt Cool</artist>
 </artists>
 <groups>
  
 </groups>
 
 <tags>
  <tag>Eurochart</tag>
  
 </tags>
 <links>
 
 </links>
</song>