<?xml version="1.0" encoding="UTF-8"?>

<song id="29531">
 <title>Kin-Dza-Dza dancerz :)</title>
 <status v="A">Active</status>
 <bitrate>256</bitrate>
 <samplerate>48000</samplerate>
 <rating votes="48">3.1458</rating>
 <info>[url=http://en.wikipedia.org/wiki/Kin-dza-dza!]Kin-Dza-Dza[/url]

The lyrics in this song are quotes from russian film &#34;Kin-Dza-Dza!&#34;.
Think of it like of a Russian anti-Star-Trek in a single film.

===========

- Плюк - чатланская планета!

- Танцуют все!
- Ку!

- Пепелац может только так летать...
- Цапу надо крутить, цапу!
- Пацаки, почему не в намордниках?
- Мне нельзя, я чатланин.

- У тебя в голове мозги или кю?

- Клади КЦ, получишь гравицапу.
- КЦ очень дорогое, родной.

- Пацак пацака не обманывает, это некрасиво, родной!
- Дикари, плакать хочется!
- Плевать... не нужно.
- Ну и зараза же ты, родной...

- ВСЕМ ЛЕЖАТЬ! ПОЛЧАСА!
- Мы - пацаки с планеты Земля.
- Ну, чего новенького-то на Плюке?

- Клади КЦ, получишь гравицапу.
- КЦ очень дорогое, родной.

===========

A bad attempt to translate this:

- Pluke is a Chatlanian planet!

- Everybody dance!
- Koo!

- A pepelatz can fly only like this...
- You must turn the tsapa! The tsapa!
- Patsaks, why are you not wearing muzzles?
- I can&#39;t, I&#39;m a Chatlanian.

- What do you have in your head, brains or kyu?

- Give us Ka-Tse, and you&#39;ll have a gravitsapa.
- Ka-Tse is very expensive, my dear...

- A Patsak doesn&#39;t lie to a Patsak! That&#39;s bad, my dear!
- Savage people... I&#39;m nearly weeping...
- Spitting... No need for it.
- What a pest you are, my dear...

- EVERYBODY LAY ON THE FLOOR! FOR HALF AN HOUR!
- We are the Patsaks from the planet Earth.
- Well, what&#39;s new on Pluke?

- Give us Ka-Tse, and you&#39;ll have a gravitsapa.
- Ka-Tse is very expensive, my dear..</info>
 <songlength>220</songlength>
 <locked>True</locked>
 <locked_until>2018-07-22 08:56:45</locked_until>
 <lastplayed>2018-06-11 16:08:24</lastplayed>
 <platform id="8">IT</platform>
 <type id="3">Oldskool</type>
 <pouetid>54121</pouetid>
 
 
 
 <artists>
  <artist id="4322">Vedem</artist>
 </artists>
 <groups>
  
 </groups>
 
 <tags>
  <tag>Lyrics</tag>
  
  <tag>RussianSpeak</tag>
  
 </tags>
 <links>
 
 </links>
</song>