<?xml version="1.0" encoding="UTF-8"?>

<song id="3211">
 <title>Lazy Jones</title>
 <status v="A">Active</status>
 <bitrate>128</bitrate>
 <samplerate>44100</samplerate>
 <rating votes="84">4.0357</rating>
 
 <songlength>234</songlength>
 <locked>False</locked>
 <locked_until>2018-06-09 16:26:09</locked_until>
 <lastplayed>2018-05-06 23:26:38</lastplayed>
 
 
 
 
 
 
 <artists>
  <artist id="550">Instant Remedy</artist>
 </artists>
 <groups>
  
 </groups>
 
 <tags>
  <tag>GameRemix</tag>
  
 </tags>
 <links>
 
 </links>
</song>