<?xml version="1.0" encoding="UTF-8"?>

<song id="44911">
 <title>Suspicion</title>
 <status v="A">Active</status>
 <bitrate>256</bitrate>
 <samplerate>44100</samplerate>
 <rating votes="5">1.4</rating>
 <info>12th in the Chaos Constructions 2015 Multichannel Traditional Music competition</info>
 <songlength>100</songlength>
 <locked>True</locked>
 <locked_until>2018-06-21 08:12:39</locked_until>
 <lastplayed>2018-05-25 19:28:15</lastplayed>
 
 <type id="4">Compo Entry</type>
 
 
 
 
 <artists>
  <artist id="5799">Ap.t</artist>
 </artists>
 <groups>
  
 </groups>
 
 <tags>
  <tag>ChaosConstructions</tag>
  
 </tags>
 <links>
 
  <link>
    <url>https://demozoo.org/music/146039/</url>
    <comment></comment>
    <type id="23">
        <name>Demozoo</name>
        <icon>/static/media/linkicons/demozoo-16x16_RJXlval.png</icon>
    </type>
  </link>
 
  <link>
    <url>https://demozoo.org/music/146040/</url>
    <comment></comment>
    <type id="23">
        <name>Demozoo</name>
        <icon>/static/media/linkicons/demozoo-16x16_RJXlval.png</icon>
    </type>
  </link>
 
  <link>
    <url>https://demozoo.org/music/146040/</url>
    <comment></comment>
    <type id="23">
        <name>Demozoo</name>
        <icon>/static/media/linkicons/demozoo-16x16_RJXlval.png</icon>
    </type>
  </link>
 
 </links>
</song>