<?xml version="1.0" encoding="UTF-8"?>

<song id="33084">
 <title>Short</title>
 <status v="A">Active</status>
 <bitrate>320</bitrate>
 <samplerate>44100</samplerate>
 <rating votes="22">3.5909</rating>
 
 <songlength>146</songlength>
 <locked>False</locked>
 <locked_until>2018-06-10 20:19:02</locked_until>
 <lastplayed>2018-05-04 11:47:45</lastplayed>
 <platform id="6">MOD</platform>
 
 
 
 
 
 <artists>
  <artist id="1580">Walkman</artist>
 </artists>
 <groups>
  
 </groups>
 
 <tags>
 </tags>
 <links>
 
 </links>
</song>