<?xml version="1.0" encoding="UTF-8"?>

<song id="25459">
 <title>Suo</title>
 <status v="V">Not verified</status>
 <bitrate>128</bitrate>
 <samplerate>44100</samplerate>
 <rating votes="11">1.7273</rating>
 
 <songlength>369</songlength>
 <locked>True</locked>
 <locked_until>None</locked_until>
 <lastplayed>2012-09-20 07:17:12</lastplayed>
 
 
 
 
 
 
 <artists>
  <artist id="3713">Tero</artist>
 </artists>
 <groups>
  
 </groups>
 
 <tags>
  <tag>Acid</tag>
  
  <tag>Minimal</tag>
  
  <tag>minimalistic</tag>
  
  <tag>Repetitive</tag>
  
 </tags>
 <links>
 
 </links>
</song>