<?xml version="1.0" encoding="UTF-8"?>

<song id="39940">
 <title>Moonlight</title>
 <status v="A">Active</status>
 <bitrate>127</bitrate>
 <samplerate>44100</samplerate>
 <rating votes="15">3.0667</rating>
 
 <songlength>180</songlength>
 <locked>False</locked>
 <locked_until>2018-06-13 10:52:04</locked_until>
 <lastplayed>2018-05-03 15:04:17</lastplayed>
 <platform id="3">XM</platform>
 
 
 
 
 
 <artists>
  <artist id="5457">Perrra</artist>
 </artists>
 <groups>
  
 </groups>
 
 <tags>
 </tags>
 <links>
 
 </links>
</song>