<?xml version="1.0" encoding="UTF-8"?>

<song id="31956">
 <title>Parallax (space edit)</title>
 <status v="A">Active</status>
 <bitrate>320</bitrate>
 <samplerate>44100</samplerate>
 <rating votes="44">3.9091</rating>
 
 <songlength>275</songlength>
 <locked>True</locked>
 <locked_until>2018-07-04 21:03:31</locked_until>
 <lastplayed>2018-05-31 01:07:08</lastplayed>
 <platform id="1">Other</platform>
 <type id="5">Remix</type>
 
 
 
 
 <artists>
  <artist id="1815">Hazel</artist>
 </artists>
 <groups>
  
 </groups>
 
 <tags>
  <tag>GameRemix</tag>
  
  <tag>Space</tag>
  
  <tag>Untz</tag>
  
 </tags>
 <links>
 
 </links>
</song>