<?xml version="1.0" encoding="UTF-8"?>

<song id="16197">
 <title>Local hero</title>
 <status v="A">Active</status>
 <bitrate>128</bitrate>
 <samplerate>44100</samplerate>
 <rating votes="19">4.0</rating>
 
 <songlength>150</songlength>
 <locked>False</locked>
 <locked_until>2017-10-16 05:15:02</locked_until>
 <lastplayed>2017-10-11 02:09:39</lastplayed>
 <platform id="5">AY/YM</platform>
 
 
 
 
 
 <artists>
  <artist id="2458">Crazy Q</artist>
 </artists>
 <groups>
  
 </groups>
 
 <tags>
 </tags>
 <links>
 
  <link>
    <url>https://demozoo.org/music/100319/</url>
    <comment></comment>
    <type id="23">
        <name>Demozoo</name>
        <icon>/static/media/linkicons/demozoo-16x16_RJXlval.png</icon>
    </type>
  </link>
 
 </links>
</song>