<?xml version="1.0" encoding="UTF-8"?>

<song id="362">
 <title>Lunar Planetarium</title>
 <status v="A">Active</status>
 <bitrate>128</bitrate>
 <samplerate>44100</samplerate>
 <rating votes="40">3.8</rating>
 
 <songlength>474</songlength>
 <locked>True</locked>
 <locked_until>2018-06-20 06:57:40</locked_until>
 <lastplayed>2018-05-14 21:24:18</lastplayed>
 
 
 
 
 
 
 <artists>
  <artist id="1313">Aural Planet</artist>
 </artists>
 <groups>
  
 </groups>
 
 <tags>
  <tag>long</tag>
  
  <tag>Progressive</tag>
  
  <tag>Psytrance</tag>
  
  <tag>Techno</tag>
  
  <tag>vocoder</tag>
  
 </tags>
 <links>
 
 </links>
</song>