<?xml version="1.0" encoding="UTF-8"?>

<song id="43934">
 <title>LifeStruck</title>
 <status v="A">Active</status>
 <bitrate>851</bitrate>
 <samplerate>48000</samplerate>
 <rating votes="14">2.3571</rating>
 <info>───────────────────────────

Do not be fooled by the
funky sample names! These
are the same samples I&#39;ve
ripped and kept for half a
year! :-)

After finals are over this
week and I get home, I
promise I will rip a new
set of samples (double :-))
───────────────────────────

      - Lifestruck -

  ─═ by PhoenIx / kLf ═─
     December 13, 1994

 composed in ScreamTracker
 3.2, it&#39;s the fourth time
      I&#39;ve run ST.EXE!
───────────────────────────

Look at all this room for
greets!

Leviathan: finish that 87!
Hadji: Hadji!!!! (doesn&#39;t
 everyone say that?) :)
Zer0: How about some REAL
 Indystrial Rage?
Musicman: Keep Bass alive!
Neurosis: You&#39;ll be
 recognizing some of these
 samples very soon :-)
Stalker: Are the $5 checks
 pouring in yet? hehe
Maelcum: Waiting for that
 KLF XMas surprise!
Scoobs: I still think the
 audio CD is a good idea!
Skaven: Pamela Anderson&#39;s
 #1 fan.. no gifs at ASM95!
and.. necros uuDW rangeRick
 sophisto &amp; the #trax gang!
───────────────────────────

 ·Andy Voss·vossa_rpi.edu·
      happy holidaze</info>
 <songlength>277</songlength>
 <locked>False</locked>
 <locked_until>2018-06-05 19:41:00</locked_until>
 <lastplayed>2018-04-18 04:21:39</lastplayed>
 <platform id="7">S3M</platform>
 <type id="3">Oldskool</type>
 
 
 
 
 <artists>
  <artist id="926">Phoenix [US]</artist>
 </artists>
 <groups>
  
 </groups>
 
 <tags>
  <tag>boring</tag>
  
  <tag>OutOfTune</tag>
  
  <tag>Repetitive</tag>
  
  <tag>TruckDriversGearChange</tag>
  
 </tags>
 <links>
 
  <link>
    <url>https://modarchive.org/module.php?70272</url>
    <comment></comment>
    <type id="24">
        <name>ModArchive</name>
        <icon>/static/media/linkicons/modarchive_Hns9j6v.png</icon>
    </type>
  </link>
 
 </links>
</song>