<?xml version="1.0" encoding="UTF-8"?>

<song id="22552">
 <title>Engage Warp 1</title>
 <status v="A">Active</status>
 <bitrate>128</bitrate>
 <samplerate>44100</samplerate>
 <rating votes="15">3.0667</rating>
 
 <songlength>211</songlength>
 <locked>False</locked>
 <locked_until>None</locked_until>
 <lastplayed>2017-03-09 22:12:32</lastplayed>
 <platform id="6">MOD</platform>
 <type id="3">Oldskool</type>
 
 
 
 
 <artists>
  <artist id="904">Parsec</artist>
 </artists>
 <groups>
  
 </groups>
 
 <tags>
 </tags>
 <links>
 
 </links>
</song>