<?xml version="1.0" encoding="UTF-8"?>

<song id="5038">
 <title>Acidi2</title>
 <status v="A">Active</status>
 <bitrate>128</bitrate>
 <samplerate>44100</samplerate>
 <rating votes="22">3.2727</rating>
 
 <songlength>126</songlength>
 <locked>False</locked>
 <locked_until>2018-06-03 15:11:09</locked_until>
 <lastplayed>2018-05-14 05:24:38</lastplayed>
 <platform id="6">MOD</platform>
 <type id="2">Demo</type>
 <pouetid>2370</pouetid>
 <ytid>-41IsNVRV8k</ytid>
 
 
 <artists>
  <artist id="828">Muffler</artist>
 </artists>
 <groups>
  
 </groups>
 
 <tags>
 </tags>
 <links>
 
 </links>
</song>