<?xml version="1.0" encoding="UTF-8"?>

<song id="38474">
 <title>Flumbo&#39;s Hest</title>
 <status v="A">Active</status>
 <bitrate>192</bitrate>
 <samplerate>44100</samplerate>
 <rating votes="17">3.9412</rating>
 <info>http://csdb.dk/release/?id=108338</info>
 <songlength>143</songlength>
 <locked>False</locked>
 <locked_until>2018-05-06 11:40:40</locked_until>
 <lastplayed>2018-04-04 22:21:40</lastplayed>
 <platform id="2">SID </platform>
 <type id="4">Compo Entry</type>
 
 
 
 
 <artists>
  <artist id="5097">Stinsen</artist>
 </artists>
 <groups>
  <group id="653">Genesis Project</group>
 </groups>
 
 <tags>
  <tag>animal</tag>
  
 </tags>
 <links>
 
 </links>
</song>