<?xml version="1.0" encoding="UTF-8"?>

<song id="43074">
 <title>Psychodrama remix</title>
 <status v="A">Active</status>
 <bitrate>0</bitrate>
 <samplerate>44100</samplerate>
 <rating votes="9">2.4444</rating>
 <info>It may be a non qualified Saturne &#39;96 entry.</info>
 <songlength>243</songlength>
 <locked>True</locked>
 <locked_until>2018-07-26 09:48:02</locked_until>
 <lastplayed>2018-06-12 02:38:13</lastplayed>
 <platform id="3">XM</platform>
 <type id="4">Compo Entry</type>
 
 
 
 
 <artists>
  <artist id="429">Fahruz</artist>
 </artists>
 <groups>
  
 </groups>
 
 <tags>
  <tag>1996</tag>
  
  <tag>Saturne</tag>
  
 </tags>
 <links>
 
 </links>
</song>