<?xml version="1.0" encoding="UTF-8"?>

<song id="18220">
 <title>Storm front</title>
 <status v="A">Active</status>
 <bitrate>128</bitrate>
 <samplerate>44100</samplerate>
 <rating votes="12">2.9167</rating>
 
 <songlength>154</songlength>
 <locked>False</locked>
 <locked_until>2018-04-29 06:24:42</locked_until>
 <lastplayed>2018-04-07 08:52:08</lastplayed>
 
 
 
 
 
 
 <artists>
  <artist id="2736">Firelight</artist>
 </artists>
 <groups>
  
 </groups>
 
 <tags>
 </tags>
 <links>
 
 </links>
</song>