<?xml version="1.0" encoding="UTF-8"?>

<song id="23896">
 <title>The Dungeons of Avalon 1</title>
 <status v="A">Active</status>
 <bitrate>127</bitrate>
 <samplerate>44100</samplerate>
 <rating votes="11">2.0</rating>
 
 <songlength>337</songlength>
 <locked>False</locked>
 <locked_until>None</locked_until>
 <lastplayed>2017-01-10 14:46:03</lastplayed>
 <platform id="35">TFMX</platform>
 <type id="7">Game</type>
 
 
 
 
 <artists>
  <artist id="3519">Rudolf Stember</artist>
 </artists>
 <groups>
  
 </groups>
 
 <tags>
  <tag>Gamemusic</tag>
  
 </tags>
 <links>
 
 </links>
</song>