<?xml version="1.0" encoding="UTF-8"?>

<song id="12712">
 <title>Critical Wound</title>
 <status v="A">Active</status>
 <bitrate>127</bitrate>
 <samplerate>44100</samplerate>
 <rating votes="51">4.3922</rating>
 
 <songlength>128</songlength>
 <locked>True</locked>
 <locked_until>2018-07-04 21:15:19</locked_until>
 <lastplayed>2018-06-04 12:36:34</lastplayed>
 <platform id="4">AHX</platform>
 <type id="1">Chiptune</type>
 
 
 
 
 <artists>
  <artist id="1327">Buzzer</artist>
 </artists>
 <groups>
  <group id="25">Brainstorm</group>
 </groups>
 
 <tags>
  <tag>OldSchool</tag>
  
 </tags>
 <links>
 
 </links>
</song>