<?xml version="1.0" encoding="UTF-8"?>

<song id="19904">
 <title>M  ergen c armada</title>
 <status v="A">Active</status>
 <bitrate>128</bitrate>
 <samplerate>44100</samplerate>
 <rating votes="11">1.6364</rating>
 
 <songlength>146</songlength>
 <locked>False</locked>
 <locked_until>2017-11-08 02:19:36</locked_until>
 <lastplayed>2017-10-26 04:51:33</lastplayed>
 
 
 
 
 
 
 <artists>
  <artist id="2981">K93</artist>
 </artists>
 <groups>
  
 </groups>
 
 <tags>
  <tag>OddStuffFromOldNecta</tag>
  
 </tags>
 <links>
 
 </links>
</song>