<?xml version="1.0" encoding="UTF-8"?>

<song id="28040">
 <title>[Deus Ex] Opponent Within</title>
 <status v="A">Active</status>
 <bitrate>128</bitrate>
 <samplerate>44100</samplerate>
 <rating votes="10">3.6</rating>
 
 <songlength>111</songlength>
 <locked>False</locked>
 <locked_until>None</locked_until>
 <lastplayed>2017-01-12 15:18:47</lastplayed>
 <platform id="8">IT</platform>
 <type id="7">Game</type>
 
 
 
 
 <artists>
  <artist id="1076">Siren</artist>
 </artists>
 <groups>
  
 </groups>
 
 <tags>
  <tag>DeusEx</tag>
  
  <tag>Gamemusic</tag>
  
 </tags>
 <links>
 
 </links>
</song>