<?xml version="1.0" encoding="UTF-8"?>

<song id="4449">
 <title>Sae02</title>
 <status v="A">Active</status>
 <bitrate>128</bitrate>
 <samplerate>44100</samplerate>
 <rating votes="13">3.0</rating>
 <info>makt1/cls.sst.sac.sae

this one&#39;s for kooty

maktone@hotmail.com
for a sae musicdisk</info>
 <songlength>31</songlength>
 <locked>False</locked>
 <locked_until>2018-05-26 16:52:32</locked_until>
 <lastplayed>2018-04-17 01:32:35</lastplayed>
 <platform id="6">MOD</platform>
 <type id="11">Musicdisk</type>
 <pouetid>1182</pouetid>
 
 
 
 <artists>
  <artist id="720">Maktone</artist>
 </artists>
 <groups>
  
 </groups>
 
 <tags>
  <tag>Short</tag>
  
 </tags>
 <links>
 
 </links>
</song>