<?xml version="1.0" encoding="UTF-8"?>

<song id="34082">
 <title>Seductive Transparency</title>
 <status v="A">Active</status>
 <bitrate>0</bitrate>
 <samplerate>0</samplerate>
 <rating votes="20">2.6</rating>
 <info>[url]http://www.explizit.org/1996/04/seductive-transparency/[/url]</info>
 <songlength>651</songlength>
 <locked>False</locked>
 <locked_until>2017-12-10 17:18:25</locked_until>
 <lastplayed>2017-11-16 15:24:55</lastplayed>
 <platform id="3">XM</platform>
 
 
 
 
 
 <artists>
  <artist id="631">KoM&#39;AH</artist>
 </artists>
 <groups>
  <group id="420">Explizit</group>
 </groups>
 
 <tags>
  <tag>long</tag>
  
 </tags>
 <links>
 
 </links>
</song>