<?xml version="1.0" encoding="UTF-8"?>

<song id="42131">
 <title>Outland</title>
 <status v="A">Active</status>
 <bitrate>0</bitrate>
 <samplerate>0</samplerate>
 <rating votes="9">3.0</rating>
 
 <songlength>156</songlength>
 <locked>False</locked>
 <locked_until>2018-01-04 14:10:48</locked_until>
 <lastplayed>2017-12-13 20:15:08</lastplayed>
 <platform id="6">MOD</platform>
 
 <pouetid>4724</pouetid>
 
 
 
 <artists>
  <artist id="2295">Bethoven</artist>
 </artists>
 <groups>
  
 </groups>
 
 <tags>
 </tags>
 <links>
 
 </links>
</song>